step06/__init__.py
step06-0.1.0.dist-info/WHEEL
step06-0.1.0.dist-info/entry_points.txt
step06-0.1.0.dist-info/METADATA
step06-0.1.0.dist-info/RECORD
