Metadata-Version: 2.3
Name: step06
Version: 0.1.0
Summary: Add your description here
Author: yaksun
Author-email: yaksun <511809501@qq.com>
Requires-Dist: mcp[cli]>=1.25.0
Requires-Python: >=3.13
